LICENSE
MANIFEST.in
README.md
pyproject.toml
setup.py
./fastvol/__init__.py
./fastvol/utils.py
./fastvol/american/__init__.py
./fastvol/american/bopm.py
./fastvol/american/bopm.pyi
./fastvol/american/neural.py
./fastvol/american/neural.pyi
./fastvol/american/psor.py
./fastvol/american/psor.pyi
./fastvol/american/ttree.py
./fastvol/american/ttree.pyi
./fastvol/european/__init__.py
./fastvol/european/bsm.py
./fastvol/european/bsm.pyi
./fastvol/european/heston.py
./fastvol/neural/__init__.py
./fastvol/neural/american.py
./fastvol/neural/training.py
./fastvol/neural/utils.py
./fastvol/neural/checkpoints/american_ivnet.pt
./fastvol/neural/checkpoints/american_vnet.pt
fastvol/__init__.py
fastvol/_core.c
fastvol/_core.pyx
fastvol/_ffi.pxd
fastvol/utils.py
fastvol/_core/.clang-format
fastvol/_core/CMakeLists.txt
fastvol/_core/bench/bench.cpp
fastvol/_core/build/CMakeCache.txt
fastvol/_core/build/Makefile
fastvol/_core/build/bench
fastvol/_core/build/cmake_install.cmake
fastvol/_core/build/CMakeFiles/CMakeConfigureLog.yaml
fastvol/_core/build/CMakeFiles/CMakeDirectoryInformation.cmake
fastvol/_core/build/CMakeFiles/CMakeRuleHashes.txt
fastvol/_core/build/CMakeFiles/InstallScripts.json
fastvol/_core/build/CMakeFiles/Makefile.cmake
fastvol/_core/build/CMakeFiles/Makefile2
fastvol/_core/build/CMakeFiles/TargetDirectories.txt
fastvol/_core/build/CMakeFiles/cmake.check_cache
fastvol/_core/build/CMakeFiles/progress.marks
fastvol/_core/build/CMakeFiles/4.0.3/CMakeCXXCompiler.cmake
fastvol/_core/build/CMakeFiles/4.0.3/CMakeDetermineCompilerABI_CXX.bin
fastvol/_core/build/CMakeFiles/4.0.3/CMakeSystem.cmake
fastvol/_core/build/CMakeFiles/4.0.3/CompilerIdCXX/CMakeCXXCompilerId.cpp
fastvol/_core/build/CMakeFiles/4.0.3/CompilerIdCXX/a.out
fastvol/_core/build/CMakeFiles/4.0.3/CompilerIdCXX/apple-sdk.cpp
fastvol/_core/build/CMakeFiles/FindOpenMP/ompver_CXX.bin
fastvol/_core/build/CMakeFiles/bench.dir/DependInfo.cmake
fastvol/_core/build/CMakeFiles/bench.dir/build.make
