Metadata-Version: 2.4
Name: fastvol
Version: 0.1.1
Summary: High-performance option pricing and volatility modeling library.
Author: Valerio Galanti
License-Expression: MIT
Project-URL: Homepage, https://github.com/vgalanti/fastvol
Requires-Python: >=3.10
Requires-Dist: torch>=2.3
Requires-Dist: numpy>=1.26
